xim_reader_rs-0.0.2.dist-info/METADATA
xim_reader_rs-0.0.2.dist-info/WHEEL
xim_reader_rs-0.0.2.dist-info/licenses/LICENSE
xim_reader.libs/libgcc_s-1e52349c.so.1
xim_reader/py.typed
xim_reader/__init__.py
xim_reader/xim_reader.pyi
xim_reader/xim_reader.abi3.so
xim_reader_rs-0.0.2.dist-info/RECORD
