Metadata-Version: 2.4
Name: xim_reader_rs
Version: 0.0.2
Classifier: Programming Language :: Rust
Classifier: Programming Language :: Python :: Implementation :: CPython
Classifier: Programming Language :: Python :: Implementation :: PyPy
Requires-Dist: numpy>=1.20.3,<2.0
License-File: LICENSE
Summary: Parse the XIM image format from Varian
Author-email: purepani <purepani@pm.me>
License: MIT
Requires-Python: >=3.8
Project-URL: Homepage, https://github.com/purepani/xim_reader
